LICENSE.txt
README.rst
setup.cfg
setup.py
viboon555/Myprofile.py
viboon555/__init__.py
viboon555.egg-info/PKG-INFO
viboon555.egg-info/SOURCES.txt
viboon555.egg-info/dependency_links.txt
viboon555.egg-info/top_level.txt